local_reload/__init__.py
local_reload/__pycache__/__init__.cpython-37.pyc
local_reload/static/local_reload/local_reload.js
local_reload/static/local_reload/vendor/NavTricks/.git
local_reload/static/local_reload/vendor/NavTricks/LICENSE
local_reload/static/local_reload/vendor/NavTricks/NavTricks.js
local_reload/static/local_reload/vendor/NavTricks/README.md
local_reload/static/local_reload/vendor/NavTricks/VERSION
local_reload/static/local_reload/vendor/NavTricks/back-or-up-button.js
local_reload/static/local_reload/vendor/NavTricks/back-or-up-link.js
local_reload/static/local_reload/vendor/NavTricks/index.html
local_reload/static/local_reload/vendor/NavTricks/release
local_reload/static/local_reload/vendor/NavTricks/demo/index.html
local_reload/static/local_reload/vendor/NavTricks/demo/a/index.html
local_reload/static/local_reload/vendor/NavTricks/releases/NavTricks-0.0.0.js
local_reload/static/local_reload/vendor/NavTricks/releases/NavTricks-0.0.1.js
local_reload/static/local_reload/vendor/NavTricks/releases/NavTricks-0.0.2.js
local_reload/static/local_reload/vendor/NavTricks/releases/NavTricks-1.0.0.js
local_reload/static/local_reload/vendor/NavTricks/releases/NavTricks-1.0.1.js
local_reload/templates/local_reload/local_reload_support.html
local_reload/templatetags/local_reload.py
local_reload/templatetags/__pycache__/local_reload.cpython-37.pyc
local_reload-1.2.4.dist-info/LICENSE
local_reload-1.2.4.dist-info/METADATA
local_reload-1.2.4.dist-info/WHEEL
local_reload-1.2.4.dist-info/top_level.txt
local_reload-1.2.4.dist-info/RECORD
