Metadata-Version: 2.1
Name: local-reload
Version: 1.2.4
Summary: Django app for automatically identifying and reloading stale web pages
Home-page: https://github.com/quadrant-newmedia/local_reload
Author: Alex Fischer
Author-email: alex@quadrant.net
License: UNKNOWN
Platform: UNKNOWN
Classifier: Programming Language :: Python :: 3
Classifier: License :: OSI Approved :: MIT License
Classifier: Operating System :: OS Independent
Requires-Python: >=3.6
Requires-Dist: Django (<3.1,>=2.2)
